{
  "id": "becas-minciencias",
  "title": "Postulación Doctorado - Minciencias 975",
  "status": "active",
  "created_at": "2026-04-07",
  "updated_at": "2026-04-07",
  "description": "Plan maestro de postulación a la Convocatoria 975 Becas para el Cambio de Minciencias. Incluye la aplicación a 6 programas doctorales (Manchester, UAB, KU Leuven, Javeriana, Uninorte). Propuesta enfocada en Literacidad Crítica y Paz.",
  "tags": [
    "doctorado",
    "minciencias",
    "investigación",
    "educación",
    "literacidad"
  ],
  "path": "/Users/nestor/Documents/convocatorias/Convocatoria Becas de Doctorado minciencias",
  "recent_changes": [
    "Plan maestro de ejecución creado.",
    "Documento de propuesta base definido.",
    "Priorización de programas y sustitución de UZH por KU Leuven."
  ]
}
